runoob/v5.4_clk_switch/clk_switch.v
/*
sel_clk1_r: 这是一个三位的寄存器，用于缓存时钟选择信号sel_clk1。它在clk1的上升沿更新，每次将sel_clk1_r的低两位左移一位，
然后将sel_clk1和sel_clk2_neg_r[1]的"与"结果赋值给sel_clk1_r的最高位。
这样做的目的是为了同步另一个时钟控制信号sel_clk2_neg_r[1]和本时钟控制信号sel_clk1，避免时钟切换时出现冲突或抖动。
sel_clk1_neg_r: 这是一个两位的寄存器，用于缓存时钟选择信号sel_clk1_r[2]。
它在clk1的下降沿更新，每次将sel_clk1_neg_r的低一位左移一位，然后将sel_clk1_r[2]赋值给sel_clk1_neg_r的最高位。
这样做的目的是为了延迟一个半周期，使得在clk_out上出现时钟切换时，能够保证clk_out的上升沿和下降沿都是完整的。
*/
/*
sel_clk2_r: 这是一个三位的寄存器，用于缓存时钟选择信号!sel_clk1。它在clk2的上升沿更新，每次将sel_clk2_r的低两位左移一位，
然后将!sel_clk1和!sel_clk1_neg_r[1]的"与"结果赋值给sel_clk2_r的最高位。
这样做的目的是为了同步另一个时钟控制信号!sel_clk1_neg_r[1]和本时钟控制信号!sel_clk1，避免时钟切换时出现冲突或抖动。
sel_clk2_neg_r: 这是一个两位的寄存器，用于缓存时钟选择信号sel_clk2_r[2]。它在clk2的下降沿更新，每次将sel_clk2_neg_r的低一位左移一位，
然后将sel_clk2_r[2]赋值给sel_clk2_neg_r的最高位。这样做的目的是为了延迟一个半周期，使得在clk_out上出现时钟切换时，能够保证clk_out的上升沿和下降沿都是完整的
*/
module clk_switch(
    input               rstn ,
    input               clk1,
    input               clk2,
    input               sel_clk1 , // 1 clk1, 0 clk2
    output              clk_out
    );

   reg [2:0]            sel_clk1_r ;
   reg [1:0]            sel_clk1_neg_r ;
   reg [2:0]            sel_clk2_r ;
   reg [1:0]            sel_clk2_neg_r ;

   //sync sel clk1 signal from different clk domain, use 3 clap
   always @(posedge clk1 or negedge rstn) begin
      if (!rstn) begin
         sel_clk1_r     <= 3'b111 ;
      end
      else begin
         //sel clk1, and not sel clk2
         sel_clk1_r     <= {sel_clk1_r[1:0], sel_clk1 & (!sel_clk2_neg_r[1])} ;
      end
   end

   //at negedge capture sel clk1 signal, use 2 clap
   always @(negedge clk1 or negedge rstn) begin
      if (!rstn) begin
         sel_clk1_neg_r <= 2'b11 ;
      end
      else begin
         sel_clk1_neg_r <= {sel_clk1_neg_r[0], sel_clk1_r[2]} ;
      end
   end

   //sync sel clk2 signal from different clk domain, use 3 clap
   always @(posedge clk2 or negedge rstn) begin
      if (!rstn) begin
         sel_clk2_r     <= 3'b0 ;
      end
      else begin
         //sel clk2, and not sel clk1
         sel_clk2_r     <= {sel_clk2_r[1:0], !sel_clk1 & (!sel_clk1_neg_r[1])} ;
      end
   end

   //at negedge capture sel clk1 signal, use 2 clap
   always @(negedge clk2 or negedge rstn) begin
      if (!rstn) begin
         sel_clk2_neg_r <= 2'b0 ;
      end
      else begin
         sel_clk2_neg_r <= {sel_clk2_neg_r[0], sel_clk2_r[2]} ;
      end
   end

   //output clk
   wire clk1_gate, clk2_gate ;
   and (clk1_gate, clk1, sel_clk1_neg_r[1]) ;
   and (clk2_gate, clk2, sel_clk2_neg_r[1]) ;
   or  (clk_out, clk1_gate, clk2_gate) ;

endmodule

runoob/v5.4_clk_switch/test.v
`timescale 1ns/1ps

module test ;
   reg          clk_100mhz, clk_200mhz ;
   reg          rstn ;
   reg          sel ;
   wire         clk_out ;

   always #(2.5)    clk_200mhz  = ~clk_200mhz ;
   always @(posedge clk_200mhz)
                    clk_100mhz  = #1 ~clk_100mhz ;

   initial begin
      clk_100mhz  = 0 ;
      clk_200mhz  = 0 ;
      rstn        = 0 ;
      sel         = 1 ;
      #11 rstn    = 1 ;
      #36.2 sel   = ~sel ;
      #119.7 sel   = ~sel ;
   end

   clk_switch u_clk_switch(
     .rstn      (rstn),
     .clk1      (clk_100mhz),
     .clk2      (clk_200mhz),
     .sel_clk1  (sel),
     .clk_out   (clk_out));


   initial begin
      forever begin
         #100;
         if ($time >= 10000)  $finish ;
      end
   end
   initial begin
      $dumpfile("wave.vcd");
      $dumpvars(0);
   end

endmodule

runoob/v5.4_clk_switch/test/wave.vcd
$date
	Fri Sep 01 11:36:33 2023
$end
$version
	QuestaSim Version 10.6c
$end
$timescale
	1ps
$end

$scope module test $end
$var reg 1 ! clk_100mhz $end
$var reg 1 " clk_200mhz $end
$var reg 1 # rstn $end
$var reg 1 $ sel $end
$var wire 1 % clk_out $end

$scope module u_clk_switch $end
$var wire 1 & rstn $end
$var wire 1 ' clk1 $end
$var wire 1 ( clk2 $end
$var wire 1 ) sel_clk1 $end
$var wire 1 % clk_out $end
$var reg 3 * sel_clk1_r [2:0] $end
$var reg 2 + sel_clk1_neg_r [1:0] $end
$var reg 3 , sel_clk2_r [2:0] $end
$var reg 2 - sel_clk2_neg_r [1:0] $end
$var wire 1 . clk1_gate $end
$var wire 1 / clk2_gate $end
$upscope $end
$upscope $end
$enddefinitions $end
#0
$dumpvars
0!
0"
0#
1$
b111 *
b11 +
b0 ,
b0 -
0%
0.
0/
1)
0(
0'
0&
$end
#2500
1"
1(
#3500
1!
1'
1.
1%
#5000
0"
0(
#7500
1"
1(
#8500
0!
0'
0.
0%
#10000
0"
0(
#11000
1#
1&
#12500
1"
1(
#13500
1!
1'
1.
1%
#15000
0"
0(
#17500
1"
1(
#18500
0!
0'
0.
0%
#20000
0"
0(
#22500
1"
1(
#23500
1!
1'
1.
1%
#25000
0"
0(
#27500
1"
1(
#28500
0!
0'
0.
0%
#30000
0"
0(
#32500
1"
1(
#33500
1!
1'
1.
1%
#35000
0"
0(
#37500
1"
1(
#38500
0!
0'
0.
0%
#40000
0"
0(
#42500
1"
1(
#43500
1!
1'
1.
1%
#45000
0"
0(
#47200
0$
0)
#47500
1"
1(
#48500
0!
0'
0.
0%
#50000
0"
0(
#52500
1"
1(
#53500
1!
1'
1.
1%
b110 *
#55000
0"
0(
#57500
1"
1(
#58500
0!
0'
0.
0%
#60000
0"
0(
#62500
1"
1(
#63500
1!
1'
1.
1%
b100 *
#65000
0"
0(
#67500
1"
1(
#68500
0!
0'
0.
0%
#70000
0"
0(
#72500
1"
1(
#73500
1!
1'
1.
1%
b0 *
#75000
0"
0(
#77500
1"
1(
#78500
0!
0'
0.
0%
b10 +
#80000
0"
0(
#82500
1"
1(
#83500
1!
1'
1.
1%
#85000
0"
0(
#87500
1"
1(
#88500
0!
0'
0.
0%
b0 +
#90000
0"
0(
#92500
1"
1(
b1 ,
#93500
1!
1'
#95000
0"
0(
#97500
1"
1(
b11 ,
#98500
0!
0'
#100000
0"
0(
#102500
1"
1(
b111 ,
#103500
1!
1'
#105000
0"
0(
b1 -
#107500
1"
1(
#108500
0!
0'
#110000
0"
0(
b11 -
#112500
1"
1(
1/
1%
#113500
1!
1'
#115000
0"
0(
0/
0%
#117500
1"
1(
1/
1%
#118500
0!
0'
#120000
0"
0(
0/
0%
#122500
1"
1(
1/
1%
#123500
1!
1'
#125000
0"
0(
0/
0%
#127500
1"
1(
1/
1%
#128500
0!
0'
#130000
0"
0(
0/
0%
#132500
1"
1(
1/
1%
#133500
1!
1'
#135000
0"
0(
0/
0%
#137500
1"
1(
1/
1%
#138500
0!
0'
#140000
0"
0(
0/
0%
#142500
1"
1(
1/
1%
#143500
1!
1'
#145000
0"
0(
0/
0%
#147500
1"
1(
1/
1%
#148500
0!
0'
#150000
0"
0(
0/
0%
#152500
1"
1(
1/
1%
#153500
1!
1'
#155000
0"
0(
0/
0%
#157500
1"
1(
1/
1%
#158500
0!
0'
#160000
0"
0(
0/
0%
#162500
1"
1(
1/
1%
#163500
1!
1'
#165000
0"
0(
0/
0%
#166900
1$
1)
#167500
1"
1(
1/
1%
b110 ,
#168500
0!
0'
#170000
0"
0(
0/
0%
#172500
1"
1(
1/
1%
b100 ,
#173500
1!
1'
#175000
0"
0(
0/
0%
#177500
1"
1(
1/
1%
b0 ,
#178500
0!
0'
#180000
0"
0(
0/
0%
b10 -
#182500
1"
1(
1/
1%
#183500
1!
1'
#185000
0"
0(
0/
0%
b0 -
#187500
1"
1(
#188500
0!
0'
#190000
0"
0(
#192500
1"
1(
#193500
1!
1'
b1 *
#195000
0"
0(
#197500
1"
1(
#198500
0!
0'
#200000
0"
0(
#202500
1"
1(
#203500
1!
1'
b11 *
#205000
0"
0(
#207500
1"
1(
#208500
0!
0'
#210000
0"
0(
#212500
1"
1(
#213500
1!
1'
b111 *
#215000
0"
0(
#217500
1"
1(
#218500
0!
0'
b1 +
#220000
0"
0(
#222500
1"
1(
#223500
1!
1'
#225000
0"
0(
#227500
1"
1(
#228500
0!
0'
b11 +
