xiayuwen/mux2to1.v
module mux2to1(out,a,b,sel);
    input a,b,sel;//！注意这里的sel是输入信号，不是输出信号，所以不用reg声明
    output out;//！注意这里的out是输出信号，不是输入信号，所以不用wire声明
    reg out;
    
always @ (a or b or sel)
    begin
        if (sel == 1'b0) out = a;
        else out = b;
    end
endmodule

xiayuwen/mux2to1_tb.v
`timescale 1ns/1ps
`include "mux2to1.v"

module mux2_tb;

    // Parameters

    //Ports
    reg  a;
    reg  b;
    reg  sel;
    wire  out;

    initial begin
        a = 0;
        b = 0;
        sel = 0;
    end

    initial
    begin
        #5 a = 1;
        #5 b = 0;
        #5 sel = 1;
        #5 sel = 0;
        #5 a = 0;
        #5 a = 1;
        #5 b = 1;
        #5 sel = 1;
        #5 $finish;
        
    end
    initial 
    begin
        #5
        $strobe("$strobe excuting result: %t", $time);
        $monitor($time,,,"part:%b %b %b %b",a,b,sel,out);
        $display("$display excuting result: %t",$time);
        
        
    end

    initial
    begin
        $dumpfile("wave.vcd");        //生成的vcd文件名称
        $dumpvars(0);    //tb模块名称
    end
    mux2to1  mux2to1_inst (
                .a(a),
                .b(b),
                .sel(sel),
                .out(out)
            );

    //always #5  clk = ! clk ;

endmodule

xiayuwen/wave.vcd
$date
	Thu Jan 04 19:28:54 2024
$end
$version
	Icarus Verilog
$end
$timescale
	1ps
$end
$scope module mux2_tb $end
$var wire 1 ! out $end
$var reg 1 " a $end
$var reg 1 # b $end
$var reg 1 $ sel $end
$scope module mux2to1_inst $end
$var wire 1 " a $end
$var wire 1 # b $end
$var wire 1 $ sel $end
$var reg 1 ! out $end
$upscope $end
$upscope $end
$enddefinitions $end
$comment Show the parameter values. $end
$dumpall
$end
#0
$dumpvars
0$
0#
0"
0!
$end
#5000
1!
1"
#15000
0!
1$
#20000
1!
0$
#25000
0!
0"
#30000
1!
1"
#35000
1#
#40000
1$
